mcp_servers1234_demo/__init__.py
mcp_servers1234_demo/main.py
mcp_servers1234_demo/py.typed
mcp_servers1234_demo-0.1.10.dist-info/METADATA
mcp_servers1234_demo-0.1.10.dist-info/WHEEL
mcp_servers1234_demo-0.1.10.dist-info/entry_points.txt
mcp_servers1234_demo-0.1.10.dist-info/RECORD
