Metadata-Version: 2.4
Name: mcp-servers1234-demo
Version: 0.1.10
Summary: Add your description here
Requires-Python: >=3.10
Requires-Dist: mcp[cli]>=1.10.1
